bedrock_fm/__init__.py
bedrock_fm/ai21.py
bedrock_fm/amazon.py
bedrock_fm/anthropic.py
bedrock_fm/bedrock.py
bedrock_fm/bedrock_image.py
bedrock_fm/cohere.py
bedrock_fm/cohere_embeddings.py
bedrock_fm/exceptions/__init__.py
bedrock_fm/meta.py
bedrock_fm/mistral.py
bedrock_fm/model.py
bedrock_fm/stability.py
bedrock_fm/titan_embeddings.py
bedrock_fm-0.4.13.dist-info/LICENSE
bedrock_fm-0.4.13.dist-info/METADATA
bedrock_fm-0.4.13.dist-info/WHEEL
bedrock_fm-0.4.13.dist-info/RECORD
