Metadata-Version: 2.1
Name: bedrock_fm
Version: 0.4.13
Summary: A package to simplify interaction with Bedrock Foundation models
Home-page: https://github.com/mirai73/bedrock-fm
License: MIT
Author: Massimiliano Angelino
Requires-Python: >=3.10
Classifier: License :: OSI Approved :: MIT License
Classifier: Operating System :: OS Independent
Classifier: Programming Language :: Python :: 3
Classifier: Programming Language :: Python :: 3.10
Classifier: Programming Language :: Python :: 3.11
Classifier: Programming Language :: Python :: 3.12
Requires-Dist: attrs (>=23.1.0,<24.0.0)
Requires-Dist: boto3 (>=1.35.1,<2.0.0)
Requires-Dist: botocore (>=1.35.1,<2.0.0)
Requires-Dist: pillow (>=10.1.0,<11.0.0)
Project-URL: Repository, https://github.com/mirai73/bedrock-fm
